xpip_build/__init__.py
xpip_build/attribute.py
xpip_build/cmds/__init__.py
xpip_build/cmds/setuptools.py
xpip_build/cmds/version.py
xpip_mirror/__init__.py
xpip_mirror/attribute.py
xpip_mirror/cmds.py
xpip_mirror/util.py
xpip_mirror/config/__init__.py
xpip_mirror/config/mirrors.toml
xpip_upload/__init__.py
xpip_upload/attribute.py
xpip_upload/cmds.py
xpip_build-1.3.1.dist-info/LICENSE
xpip_build-1.3.1.dist-info/METADATA
xpip_build-1.3.1.dist-info/WHEEL
xpip_build-1.3.1.dist-info/entry_points.txt
xpip_build-1.3.1.dist-info/top_level.txt
xpip_build-1.3.1.dist-info/zip-safe
xpip_build-1.3.1.dist-info/RECORD
